{
  "TSVN.Options.ApplicationName": "TSVN",
  "TSVN.ToolBar.DisplayName": "TSVN",
  "TSVN.MainMenu.DisplayName": "&TSVN",
  "TSVN.FileMenu.DisplayName": "&TSVN File",
  "TSVN.WindowMenu.DisplayName": "&Windows",
  "TSVN.AddFileCommand.DisplayName": "&Add",
  "TSVN.BlameFileCommand.DisplayName": "&Blame...",
  "TSVN.CommitFileCommand.DisplayName": "&Commit...",
  "TSVN.DeleteFileCommand.DisplayName": "&Delete",
  "TSVN.DifferencesFileCommand.DisplayName": "&Show Differences",
  "TSVN.DiffPreviousFileCommand.DisplayName": "Diff with Previous &Version",
  "TSVN.DiskBrowserFileCommand.DisplayName": "D&isk-Browser",
  "TSVN.LockFileCommand.DisplayName": "Get L&ock...",
  "TSVN.MergeFileCommand.DisplayName": "&Merge...",
  "TSVN.PropertiesFileCommand.DisplayName": "&Properties...",
  "TSVN.RenameFileCommand.DisplayName": "Re&name",
  "TSVN.RepoBrowserFileCommand.DisplayName": "Repo-Br&owser",
  "TSVN.RevertFileCommand.DisplayName": "&Revert Changes...",
  "TSVN.ShowLogFileCommand.DisplayName": "Show &Log...",
  "TSVN.UnlockFileCommand.DisplayName": "Release Loc&k...",
  "TSVN.UpdateFileCommand.DisplayName": "&Update...",
  "TSVN.UpdateToRevisionFileCommand.DisplayName": "Update &to Revision...",
  "TSVN.ApplyPatchCommand.DisplayName": "Apply Patc&h...",
  "TSVN.BranchCommand.DisplayName": "&Branch...",
  "TSVN.CleanupCommand.DisplayName": "Clea&nup Working Copy...",
  "TSVN.CommitCommand.DisplayName": "&Commit...",
  "TSVN.CreatePatchCommand.DisplayName": "Create P&atch...",
  "TSVN.DiskBrowserCommand.DisplayName": "&Disk-Browser",
  "TSVN.LockCommand.DisplayName": "Get L&ock...",
  "TSVN.MergeCommand.DisplayName": "&Merge...",
  "TSVN.RepoBrowserCommand.DisplayName": "Re&po-Browser",
  "TSVN.RevertCommand.DisplayName": "&Revert Changes...",
  "TSVN.ShelveCommand.DisplayName": "Sh&elve...",
  "TSVN.ShowChangesCommand.DisplayName": "Sho&w Changes",
  "TSVN.ShowLogCommand.DisplayName": "Show &Log...",
  "TSVN.SwitchCommand.DisplayName": "&Switch...",
  "TSVN.UnlockCommand.DisplayName": "Release Loc&k...",
  "TSVN.UnshelveCommand.DisplayName": "Unshel&ve...",
  "TSVN.UpdateCommand.DisplayName": "&Update",
  "TSVN.UpdateToRevisionCommand.DisplayName": "Update &to Revision...",
  "TSVN.ApplyPatchToolbarCommand.DisplayName": "Apply Patch...",
  "TSVN.BranchToolbarCommand.DisplayName": "Branch...",
  "TSVN.CleanupToolbarCommand.DisplayName": "Cleanup Working Copy...",
  "TSVN.CommitToolbarCommand.DisplayName": "&Commit...",
  "TSVN.CreatePatchToolbarCommand.DisplayName": "Create Patch...",
  "TSVN.DiskBrowserToolbarCommand.DisplayName": "Disk-Browser",
  "TSVN.LockToolbarCommand.DisplayName": "Get Lock...",
  "TSVN.MergeToolbarCommand.DisplayName": "Merge...",
  "TSVN.RepoBrowserToolbarCommand.DisplayName": "Repo-Browser",
  "TSVN.RevertToolbarCommand.DisplayName": "Revert Changes...",
  "TSVN.ShelveToolbarCommand.DisplayName": "Shelve...",
  "TSVN.ShowChangesToolbarCommand.DisplayName": "Show Changes",
  "TSVN.ShowLogToolbarCommand.DisplayName": "Show Log...",
  "TSVN.SwitchToolbarCommand.DisplayName": "Switch...",
  "TSVN.UnlockToolbarCommand.DisplayName": "Release lock...",
  "TSVN.UnshelveToolbarCommand.DisplayName": "Unshelve...",
  "TSVN.UpdateToolbarCommand.DisplayName": "Update",
  "TSVN.UpdateToRevisionToolbarCommand.DisplayName": "Update To Revision...",
  "TSVN.OptionsDialogCommand.DisplayName": "&Options...",
  "TSVN.PendingChangesToolWindowCommand.DisplayName": "&Pending Changes...",
  "TSVN.RefreshToolbarCommand.DisplayName": "Refresh",
  "TSVN.HideFilesToolbarCommand.DisplayName": "Hide unversioned files and folders"
}
